{
  "project_info": {
    "project_number": "153536167266",
    "project_id": "poemasymas-469bd",
    "storage_bucket": "poemasymas-469bd.appspot.com"
  },
  "client": [
    {
      "client_info": {
        "mobilesdk_app_id": "1:153536167266:android:40b3bfa863f799d4ce003b",
        "android_client_info": {
          "package_name": "com.apppoemas.poemasymas"
        }
      },
      "oauth_client": [
        {
          "client_id": "153536167266-944e27fbfr6kvjnb4at9rst0hmvof6lb.apps.googleusercontent.com",
          "client_type": 1,
          "android_info": {
            "package_name": "com.apppoemas.poemasymas",
            "certificate_hash": "090281c84bfef48a9d1a47597738798b60f9de46"
          }
        },
        {
          "client_id": "153536167266-ta459eapdkcddrbopjujdnh9fl3pl7et.apps.googleusercontent.com",
          "client_type": 1,
          "android_info": {
            "package_name": "com.apppoemas.poemasymas",
            "certificate_hash": "0ff44244eccd3f888cd5cee54955caee932f51b9"
          }
        },
        {
          "client_id": "153536167266-tntlls7bp5uv534145dvmfnek2mpl6h8.apps.googleusercontent.com",
          "client_type": 3
        }
      ],
      "api_key": [
        {
          "current_key": "AIzaSyBwYWh7iBf9WiZZWPM5WLvy1rfKxIry5Jg"
        }
      ],
      "services": {
        "appinvite_service": {
          "other_platform_oauth_client": [
            {
              "client_id": "153536167266-tntlls7bp5uv534145dvmfnek2mpl6h8.apps.googleusercontent.com",
              "client_type": 3
            },
            {
              "client_id": "153536167266-nduuvtttn4aecgnufcs2m3pvahjsne46.apps.googleusercontent.com",
              "client_type": 2,
              "ios_info": {
                "bundle_id": "com.example.appPoemas"
              }
            }
          ]
        }
      },
      "admob_app_id": "ca-app-pub-2793000965286035~3088628659"
    }
  ],
  "configuration_version": "1"
}